{"v":3,"stories":{"base-colors--docs":{"id":"base-colors--docs","title":"Base/Colors","name":"Docs","importPath":"./components/00-base/01-colors/colors.stories.js","tags":["docs","autodocs"],"storiesImports":[],"kind":"Base/Colors","story":"Docs","parameters":{"__id":"base-colors--docs","docsOnly":true,"fileName":"./components/00-base/01-colors/colors.stories.js"}},"base-colors--palettes":{"id":"base-colors--palettes","name":"Palettes","title":"Base/Colors","importPath":"./components/00-base/01-colors/colors.stories.js","tags":["story"],"kind":"Base/Colors","story":"Palettes","parameters":{"__id":"base-colors--palettes","docsOnly":false,"fileName":"./components/00-base/01-colors/colors.stories.js"}},"base-motion--docs":{"id":"base-motion--docs","title":"Base/Motion","name":"Docs","importPath":"./components/00-base/02-motion/motion.stories.js","tags":["docs","autodocs"],"storiesImports":[],"kind":"Base/Motion","story":"Docs","parameters":{"__id":"base-motion--docs","docsOnly":true,"fileName":"./components/00-base/02-motion/motion.stories.js"}},"base-motion--usage":{"id":"base-motion--usage","name":"Usage","title":"Base/Motion","importPath":"./components/00-base/02-motion/motion.stories.js","tags":["story"],"kind":"Base/Motion","story":"Usage","parameters":{"__id":"base-motion--usage","docsOnly":false,"fileName":"./components/00-base/02-motion/motion.stories.js"}},"base-spacing--docs":{"id":"base-spacing--docs","title":"Base/Spacing","name":"Docs","importPath":"./components/00-base/04-spacing/spacing.stories.js","tags":["docs","autodocs"],"storiesImports":[],"kind":"Base/Spacing","story":"Docs","parameters":{"__id":"base-spacing--docs","docsOnly":true,"fileName":"./components/00-base/04-spacing/spacing.stories.js"}},"base-spacing--spacing":{"id":"base-spacing--spacing","name":"Spacing","title":"Base/Spacing","importPath":"./components/00-base/04-spacing/spacing.stories.js","tags":["story"],"kind":"Base/Spacing","story":"Spacing","parameters":{"__id":"base-spacing--spacing","docsOnly":false,"fileName":"./components/00-base/04-spacing/spacing.stories.js"}},"atoms-button--docs":{"id":"atoms-button--docs","title":"Atoms/Button","name":"Docs","importPath":"./components/01-atoms/buttons/buttons.stories.js","tags":["docs","autodocs"],"storiesImports":[],"kind":"Atoms/Button","story":"Docs","parameters":{"__id":"atoms-button--docs","docsOnly":true,"fileName":"./components/01-atoms/buttons/buttons.stories.js"}},"atoms-button--twig":{"id":"atoms-button--twig","name":"Twig","title":"Atoms/Button","importPath":"./components/01-atoms/buttons/buttons.stories.js","tags":["story"],"kind":"Atoms/Button","story":"Twig","parameters":{"__id":"atoms-button--twig","docsOnly":false,"fileName":"./components/01-atoms/buttons/buttons.stories.js"}},"atoms-button--twig-alt":{"id":"atoms-button--twig-alt","name":"Twig Alt","title":"Atoms/Button","importPath":"./components/01-atoms/buttons/buttons.stories.js","tags":["story"],"kind":"Atoms/Button","story":"Twig Alt","parameters":{"__id":"atoms-button--twig-alt","docsOnly":false,"fileName":"./components/01-atoms/buttons/buttons.stories.js"}},"atoms-forms--docs":{"id":"atoms-forms--docs","title":"Atoms/Forms","name":"Docs","importPath":"./components/01-atoms/forms/forms.stories.js","tags":["docs","autodocs"],"storiesImports":[],"kind":"Atoms/Forms","story":"Docs","parameters":{"__id":"atoms-forms--docs","docsOnly":true,"fileName":"./components/01-atoms/forms/forms.stories.js"}},"atoms-forms--checkboxes":{"id":"atoms-forms--checkboxes","name":"Checkboxes","title":"Atoms/Forms","importPath":"./components/01-atoms/forms/forms.stories.js","tags":["story"],"kind":"Atoms/Forms","story":"Checkboxes","parameters":{"__id":"atoms-forms--checkboxes","docsOnly":false,"fileName":"./components/01-atoms/forms/forms.stories.js"}},"atoms-forms--radio-buttons":{"id":"atoms-forms--radio-buttons","name":"Radio Buttons","title":"Atoms/Forms","importPath":"./components/01-atoms/forms/forms.stories.js","tags":["story"],"kind":"Atoms/Forms","story":"Radio Buttons","parameters":{"__id":"atoms-forms--radio-buttons","docsOnly":false,"fileName":"./components/01-atoms/forms/forms.stories.js"}},"atoms-forms--select-dropdowns":{"id":"atoms-forms--select-dropdowns","name":"Select Dropdowns","title":"Atoms/Forms","importPath":"./components/01-atoms/forms/forms.stories.js","tags":["story"],"kind":"Atoms/Forms","story":"Select Dropdowns","parameters":{"__id":"atoms-forms--select-dropdowns","docsOnly":false,"fileName":"./components/01-atoms/forms/forms.stories.js"}},"atoms-forms--textfields-examples":{"id":"atoms-forms--textfields-examples","name":"Textfields Examples","title":"Atoms/Forms","importPath":"./components/01-atoms/forms/forms.stories.js","tags":["story"],"kind":"Atoms/Forms","story":"Textfields Examples","parameters":{"__id":"atoms-forms--textfields-examples","docsOnly":false,"fileName":"./components/01-atoms/forms/forms.stories.js"}},"atoms-images--docs":{"id":"atoms-images--docs","title":"Atoms/Images","name":"Docs","importPath":"./components/01-atoms/images/images.stories.js","tags":["docs","autodocs"],"storiesImports":[],"kind":"Atoms/Images","story":"Docs","parameters":{"__id":"atoms-images--docs","docsOnly":true,"fileName":"./components/01-atoms/images/images.stories.js"}},"atoms-images--images":{"id":"atoms-images--images","name":"Images","title":"Atoms/Images","importPath":"./components/01-atoms/images/images.stories.js","tags":["story"],"kind":"Atoms/Images","story":"Images","parameters":{"__id":"atoms-images--images","docsOnly":false,"fileName":"./components/01-atoms/images/images.stories.js"}},"atoms-images--figures":{"id":"atoms-images--figures","name":"Figures","title":"Atoms/Images","importPath":"./components/01-atoms/images/images.stories.js","tags":["story"],"kind":"Atoms/Images","story":"Figures","parameters":{"__id":"atoms-images--figures","docsOnly":false,"fileName":"./components/01-atoms/images/images.stories.js"}},"atoms-images--icons":{"id":"atoms-images--icons","name":"Icons","title":"Atoms/Images","importPath":"./components/01-atoms/images/images.stories.js","tags":["story"],"kind":"Atoms/Images","story":"Icons","parameters":{"__id":"atoms-images--icons","docsOnly":false,"fileName":"./components/01-atoms/images/images.stories.js"}},"atoms-links--docs":{"id":"atoms-links--docs","title":"Atoms/Links","name":"Docs","importPath":"./components/01-atoms/links/link/links.stories.js","tags":["docs","autodocs"],"storiesImports":[],"kind":"Atoms/Links","story":"Docs","parameters":{"__id":"atoms-links--docs","docsOnly":true,"fileName":"./components/01-atoms/links/link/links.stories.js"}},"atoms-links--links":{"id":"atoms-links--links","name":"Links","title":"Atoms/Links","importPath":"./components/01-atoms/links/link/links.stories.js","tags":["story"],"kind":"Atoms/Links","story":"Links","parameters":{"__id":"atoms-links--links","docsOnly":false,"fileName":"./components/01-atoms/links/link/links.stories.js"}},"atoms-lists--docs":{"id":"atoms-lists--docs","title":"Atoms/Lists","name":"Docs","importPath":"./components/01-atoms/lists/list.stories.js","tags":["docs","autodocs"],"storiesImports":[],"kind":"Atoms/Lists","story":"Docs","parameters":{"__id":"atoms-lists--docs","docsOnly":true,"fileName":"./components/01-atoms/lists/list.stories.js"}},"atoms-lists--unordered-list":{"id":"atoms-lists--unordered-list","name":"Unordered List","title":"Atoms/Lists","importPath":"./components/01-atoms/lists/list.stories.js","tags":["story"],"kind":"Atoms/Lists","story":"Unordered List","parameters":{"__id":"atoms-lists--unordered-list","docsOnly":false,"fileName":"./components/01-atoms/lists/list.stories.js"}},"atoms-lists--ordered-list":{"id":"atoms-lists--ordered-list","name":"Ordered List","title":"Atoms/Lists","importPath":"./components/01-atoms/lists/list.stories.js","tags":["story"],"kind":"Atoms/Lists","story":"Ordered List","parameters":{"__id":"atoms-lists--ordered-list","docsOnly":false,"fileName":"./components/01-atoms/lists/list.stories.js"}},"atoms-lists--description-list":{"id":"atoms-lists--description-list","name":"Description List","title":"Atoms/Lists","importPath":"./components/01-atoms/lists/list.stories.js","tags":["story"],"kind":"Atoms/Lists","story":"Description List","parameters":{"__id":"atoms-lists--description-list","docsOnly":false,"fileName":"./components/01-atoms/lists/list.stories.js"}},"atoms-tables--docs":{"id":"atoms-tables--docs","title":"Atoms/Tables","name":"Docs","importPath":"./components/01-atoms/tables/tables.stories.js","tags":["docs","autodocs"],"storiesImports":[],"kind":"Atoms/Tables","story":"Docs","parameters":{"__id":"atoms-tables--docs","docsOnly":true,"fileName":"./components/01-atoms/tables/tables.stories.js"}},"atoms-tables--tables":{"id":"atoms-tables--tables","name":"Tables","title":"Atoms/Tables","importPath":"./components/01-atoms/tables/tables.stories.js","tags":["story"],"kind":"Atoms/Tables","story":"Tables","parameters":{"__id":"atoms-tables--tables","docsOnly":false,"fileName":"./components/01-atoms/tables/tables.stories.js"}},"atoms-text--docs":{"id":"atoms-text--docs","title":"Atoms/Text","name":"Docs","importPath":"./components/01-atoms/text/text.stories.js","tags":["docs","autodocs"],"storiesImports":[],"kind":"Atoms/Text","story":"Docs","parameters":{"__id":"atoms-text--docs","docsOnly":true,"fileName":"./components/01-atoms/text/text.stories.js"}},"atoms-text--headings-examples":{"id":"atoms-text--headings-examples","name":"Headings Examples","title":"Atoms/Text","importPath":"./components/01-atoms/text/text.stories.js","tags":["story"],"kind":"Atoms/Text","story":"Headings Examples","parameters":{"__id":"atoms-text--headings-examples","docsOnly":false,"fileName":"./components/01-atoms/text/text.stories.js"}},"atoms-text--blockquote-example":{"id":"atoms-text--blockquote-example","name":"Blockquote Example","title":"Atoms/Text","importPath":"./components/01-atoms/text/text.stories.js","tags":["story"],"kind":"Atoms/Text","story":"Blockquote Example","parameters":{"__id":"atoms-text--blockquote-example","docsOnly":false,"fileName":"./components/01-atoms/text/text.stories.js"}},"atoms-text--preformatted":{"id":"atoms-text--preformatted","name":"Preformatted","title":"Atoms/Text","importPath":"./components/01-atoms/text/text.stories.js","tags":["story"],"kind":"Atoms/Text","story":"Preformatted","parameters":{"__id":"atoms-text--preformatted","docsOnly":false,"fileName":"./components/01-atoms/text/text.stories.js"}},"atoms-text--random":{"id":"atoms-text--random","name":"Random","title":"Atoms/Text","importPath":"./components/01-atoms/text/text.stories.js","tags":["story"],"kind":"Atoms/Text","story":"Random","parameters":{"__id":"atoms-text--random","docsOnly":false,"fileName":"./components/01-atoms/text/text.stories.js"}},"atoms-text--code-example":{"id":"atoms-text--code-example","name":"Code Example","title":"Atoms/Text","importPath":"./components/01-atoms/text/text.stories.js","tags":["story"],"kind":"Atoms/Text","story":"Code Example","parameters":{"__id":"atoms-text--code-example","docsOnly":false,"fileName":"./components/01-atoms/text/text.stories.js"}},"atoms-tooltip--docs":{"id":"atoms-tooltip--docs","title":"Atoms/Tooltip","name":"Docs","importPath":"./components/01-atoms/tooltip/tooltip.stories.js","tags":["docs","autodocs"],"storiesImports":[],"kind":"Atoms/Tooltip","story":"Docs","parameters":{"__id":"atoms-tooltip--docs","docsOnly":true,"fileName":"./components/01-atoms/tooltip/tooltip.stories.js"}},"atoms-tooltip--tooltip-example":{"id":"atoms-tooltip--tooltip-example","name":"Tooltip Example","title":"Atoms/Tooltip","importPath":"./components/01-atoms/tooltip/tooltip.stories.js","tags":["story"],"kind":"Atoms/Tooltip","story":"Tooltip Example","parameters":{"__id":"atoms-tooltip--tooltip-example","docsOnly":false,"fileName":"./components/01-atoms/tooltip/tooltip.stories.js"}},"atoms-videos--docs":{"id":"atoms-videos--docs","title":"Atoms/Videos","name":"Docs","importPath":"./components/01-atoms/videos/videos.stories.js","tags":["docs","autodocs"],"storiesImports":[],"kind":"Atoms/Videos","story":"Docs","parameters":{"__id":"atoms-videos--docs","docsOnly":true,"fileName":"./components/01-atoms/videos/videos.stories.js"}},"atoms-videos--embed":{"id":"atoms-videos--embed","name":"Embed","title":"Atoms/Videos","importPath":"./components/01-atoms/videos/videos.stories.js","tags":["story"],"kind":"Atoms/Videos","story":"Embed","parameters":{"__id":"atoms-videos--embed","docsOnly":false,"fileName":"./components/01-atoms/videos/videos.stories.js"}},"atoms-videos--html-5":{"id":"atoms-videos--html-5","name":"Html 5","title":"Atoms/Videos","importPath":"./components/01-atoms/videos/videos.stories.js","tags":["story"],"kind":"Atoms/Videos","story":"Html 5","parameters":{"__id":"atoms-videos--html-5","docsOnly":false,"fileName":"./components/01-atoms/videos/videos.stories.js"}},"molecules-accordion--docs":{"id":"molecules-accordion--docs","title":"Molecules/Accordion","name":"Docs","importPath":"./components/02-molecules/accordion/accordion.stories.js","tags":["docs","autodocs"],"storiesImports":[],"kind":"Molecules/Accordion","story":"Docs","parameters":{"__id":"molecules-accordion--docs","docsOnly":true,"fileName":"./components/02-molecules/accordion/accordion.stories.js"}},"molecules-accordion--accordion":{"id":"molecules-accordion--accordion","name":"Accordion","title":"Molecules/Accordion","importPath":"./components/02-molecules/accordion/accordion.stories.js","tags":["story"],"kind":"Molecules/Accordion","story":"Accordion","parameters":{"__id":"molecules-accordion--accordion","docsOnly":false,"fileName":"./components/02-molecules/accordion/accordion.stories.js"}},"molecules-alert--docs":{"id":"molecules-alert--docs","title":"Molecules/Alert","name":"Docs","importPath":"./components/02-molecules/alert/alert.stories.js","tags":["docs","autodocs"],"storiesImports":[],"kind":"Molecules/Alert","story":"Docs","parameters":{"__id":"molecules-alert--docs","docsOnly":true,"fileName":"./components/02-molecules/alert/alert.stories.js"}},"molecules-alert--alert":{"id":"molecules-alert--alert","name":"Alert","title":"Molecules/Alert","importPath":"./components/02-molecules/alert/alert.stories.js","tags":["story"],"kind":"Molecules/Alert","story":"Alert","parameters":{"__id":"molecules-alert--alert","docsOnly":false,"fileName":"./components/02-molecules/alert/alert.stories.js"}},"molecules-alert--alert-examples":{"id":"molecules-alert--alert-examples","name":"Alert Examples","title":"Molecules/Alert","importPath":"./components/02-molecules/alert/alert.stories.js","tags":["story"],"kind":"Molecules/Alert","story":"Alert Examples","parameters":{"__id":"molecules-alert--alert-examples","docsOnly":false,"fileName":"./components/02-molecules/alert/alert.stories.js"}},"molecules-cards--docs":{"id":"molecules-cards--docs","title":"Molecules/Cards","name":"Docs","importPath":"./components/02-molecules/card/cards.stories.js","tags":["docs","autodocs"],"storiesImports":[],"kind":"Molecules/Cards","story":"Docs","parameters":{"__id":"molecules-cards--docs","docsOnly":true,"fileName":"./components/02-molecules/card/cards.stories.js"}},"molecules-cards--card-example":{"id":"molecules-cards--card-example","name":"Card Example","title":"Molecules/Cards","importPath":"./components/02-molecules/card/cards.stories.js","tags":["story"],"kind":"Molecules/Cards","story":"Card Example","parameters":{"__id":"molecules-cards--card-example","docsOnly":false,"fileName":"./components/02-molecules/card/cards.stories.js"}},"molecules-cards--card-with-background":{"id":"molecules-cards--card-with-background","name":"Card With Background","title":"Molecules/Cards","importPath":"./components/02-molecules/card/cards.stories.js","tags":["story"],"kind":"Molecules/Cards","story":"Card With Background","parameters":{"__id":"molecules-cards--card-with-background","docsOnly":false,"fileName":"./components/02-molecules/card/cards.stories.js"}},"molecules-cta--docs":{"id":"molecules-cta--docs","title":"Molecules/CTA","name":"Docs","importPath":"./components/02-molecules/cta/ctas.stories.js","tags":["docs","autodocs"],"storiesImports":[],"kind":"Molecules/CTA","story":"Docs","parameters":{"__id":"molecules-cta--docs","docsOnly":true,"fileName":"./components/02-molecules/cta/ctas.stories.js"}},"molecules-cta--cta-example":{"id":"molecules-cta--cta-example","name":"Cta Example","title":"Molecules/CTA","importPath":"./components/02-molecules/cta/ctas.stories.js","tags":["story"],"kind":"Molecules/CTA","story":"Cta Example","parameters":{"__id":"molecules-cta--cta-example","docsOnly":false,"fileName":"./components/02-molecules/cta/ctas.stories.js"}},"molecules-logo--docs":{"id":"molecules-logo--docs","title":"Molecules/Logo","name":"Docs","importPath":"./components/02-molecules/logo/logo.stories.js","tags":["docs","autodocs"],"storiesImports":[],"kind":"Molecules/Logo","story":"Docs","parameters":{"__id":"molecules-logo--docs","docsOnly":true,"fileName":"./components/02-molecules/logo/logo.stories.js"}},"molecules-logo--logo":{"id":"molecules-logo--logo","name":"Logo","title":"Molecules/Logo","importPath":"./components/02-molecules/logo/logo.stories.js","tags":["story"],"kind":"Molecules/Logo","story":"Logo","parameters":{"__id":"molecules-logo--logo","docsOnly":false,"fileName":"./components/02-molecules/logo/logo.stories.js"}},"molecules-menus--docs":{"id":"molecules-menus--docs","title":"Molecules/Menus","name":"Docs","importPath":"./components/02-molecules/menus/menus.stories.js","tags":["docs","autodocs"],"storiesImports":[],"kind":"Molecules/Menus","story":"Docs","parameters":{"__id":"molecules-menus--docs","docsOnly":true,"fileName":"./components/02-molecules/menus/menus.stories.js"}},"molecules-menus--breadcrumbs":{"id":"molecules-menus--breadcrumbs","name":"Breadcrumbs","title":"Molecules/Menus","importPath":"./components/02-molecules/menus/menus.stories.js","tags":["story"],"kind":"Molecules/Menus","story":"Breadcrumbs","parameters":{"__id":"molecules-menus--breadcrumbs","docsOnly":false,"fileName":"./components/02-molecules/menus/menus.stories.js"}},"molecules-menus--inline":{"id":"molecules-menus--inline","name":"Inline","title":"Molecules/Menus","importPath":"./components/02-molecules/menus/menus.stories.js","tags":["story"],"kind":"Molecules/Menus","story":"Inline","parameters":{"__id":"molecules-menus--inline","docsOnly":false,"fileName":"./components/02-molecules/menus/menus.stories.js"}},"molecules-menus--main":{"id":"molecules-menus--main","name":"Main","title":"Molecules/Menus","importPath":"./components/02-molecules/menus/menus.stories.js","tags":["story"],"kind":"Molecules/Menus","story":"Main","parameters":{"__id":"molecules-menus--main","docsOnly":false,"fileName":"./components/02-molecules/menus/menus.stories.js"}},"molecules-menus--social":{"id":"molecules-menus--social","name":"Social","title":"Molecules/Menus","importPath":"./components/02-molecules/menus/menus.stories.js","tags":["story"],"kind":"Molecules/Menus","story":"Social","parameters":{"__id":"molecules-menus--social","docsOnly":false,"fileName":"./components/02-molecules/menus/menus.stories.js"}},"molecules-menus-pager--docs":{"id":"molecules-menus-pager--docs","title":"Molecules/Menus/Pager","name":"Docs","importPath":"./components/02-molecules/pager/pager.stories.js","tags":["docs","autodocs"],"storiesImports":[],"kind":"Molecules/Menus/Pager","story":"Docs","parameters":{"__id":"molecules-menus-pager--docs","docsOnly":true,"fileName":"./components/02-molecules/pager/pager.stories.js"}},"molecules-menus-pager--basic":{"id":"molecules-menus-pager--basic","name":"Basic","title":"Molecules/Menus/Pager","importPath":"./components/02-molecules/pager/pager.stories.js","tags":["story"],"kind":"Molecules/Menus/Pager","story":"Basic","parameters":{"__id":"molecules-menus-pager--basic","docsOnly":false,"fileName":"./components/02-molecules/pager/pager.stories.js"}},"molecules-menus-pager--with-next":{"id":"molecules-menus-pager--with-next","name":"With Next","title":"Molecules/Menus/Pager","importPath":"./components/02-molecules/pager/pager.stories.js","tags":["story"],"kind":"Molecules/Menus/Pager","story":"With Next","parameters":{"__id":"molecules-menus-pager--with-next","docsOnly":false,"fileName":"./components/02-molecules/pager/pager.stories.js"}},"molecules-menus-pager--with-both":{"id":"molecules-menus-pager--with-both","name":"With Both","title":"Molecules/Menus/Pager","importPath":"./components/02-molecules/pager/pager.stories.js","tags":["story"],"kind":"Molecules/Menus/Pager","story":"With Both","parameters":{"__id":"molecules-menus-pager--with-both","docsOnly":false,"fileName":"./components/02-molecules/pager/pager.stories.js"}},"molecules-menus-pager--with-previous":{"id":"molecules-menus-pager--with-previous","name":"With Previous","title":"Molecules/Menus/Pager","importPath":"./components/02-molecules/pager/pager.stories.js","tags":["story"],"kind":"Molecules/Menus/Pager","story":"With Previous","parameters":{"__id":"molecules-menus-pager--with-previous","docsOnly":false,"fileName":"./components/02-molecules/pager/pager.stories.js"}},"molecules-menus-pager--with-first-and-last":{"id":"molecules-menus-pager--with-first-and-last","name":"With First And Last","title":"Molecules/Menus/Pager","importPath":"./components/02-molecules/pager/pager.stories.js","tags":["story"],"kind":"Molecules/Menus/Pager","story":"With First And Last","parameters":{"__id":"molecules-menus-pager--with-first-and-last","docsOnly":false,"fileName":"./components/02-molecules/pager/pager.stories.js"}},"molecules-pull-quote--docs":{"id":"molecules-pull-quote--docs","title":"Molecules/Pull Quote","name":"Docs","importPath":"./components/02-molecules/pull-quote/pull-quote.stories.js","tags":["docs","autodocs"],"storiesImports":[],"kind":"Molecules/Pull Quote","story":"Docs","parameters":{"__id":"molecules-pull-quote--docs","docsOnly":true,"fileName":"./components/02-molecules/pull-quote/pull-quote.stories.js"}},"molecules-pull-quote--pull-quote":{"id":"molecules-pull-quote--pull-quote","name":"Pull Quote","title":"Molecules/Pull Quote","importPath":"./components/02-molecules/pull-quote/pull-quote.stories.js","tags":["story"],"kind":"Molecules/Pull Quote","story":"Pull Quote","parameters":{"__id":"molecules-pull-quote--pull-quote","docsOnly":false,"fileName":"./components/02-molecules/pull-quote/pull-quote.stories.js"}},"molecules-status--docs":{"id":"molecules-status--docs","title":"Molecules/Status","name":"Docs","importPath":"./components/02-molecules/status/status.stories.js","tags":["docs","autodocs"],"storiesImports":[],"kind":"Molecules/Status","story":"Docs","parameters":{"__id":"molecules-status--docs","docsOnly":true,"fileName":"./components/02-molecules/status/status.stories.js"}},"molecules-status--status-examples":{"id":"molecules-status--status-examples","name":"Status Examples","title":"Molecules/Status","importPath":"./components/02-molecules/status/status.stories.js","tags":["story"],"kind":"Molecules/Status","story":"Status Examples","parameters":{"__id":"molecules-status--status-examples","docsOnly":false,"fileName":"./components/02-molecules/status/status.stories.js"}},"molecules-tabs--docs":{"id":"molecules-tabs--docs","title":"Molecules/Tabs","name":"Docs","importPath":"./components/02-molecules/tabs/tabs.stories.js","tags":["docs","autodocs"],"storiesImports":[],"kind":"Molecules/Tabs","story":"Docs","parameters":{"__id":"molecules-tabs--docs","docsOnly":true,"fileName":"./components/02-molecules/tabs/tabs.stories.js"}},"molecules-tabs--js-tabs":{"id":"molecules-tabs--js-tabs","name":"JS Tabs","title":"Molecules/Tabs","importPath":"./components/02-molecules/tabs/tabs.stories.js","tags":["story"],"kind":"Molecules/Tabs","story":"JS Tabs","parameters":{"__id":"molecules-tabs--js-tabs","docsOnly":false,"fileName":"./components/02-molecules/tabs/tabs.stories.js"}},"molecules-text-with-media--docs":{"id":"molecules-text-with-media--docs","title":"Molecules/Text With Media","name":"Docs","importPath":"./components/02-molecules/text-with-media/text-with-media.stories.js","tags":["docs","autodocs"],"storiesImports":[],"kind":"Molecules/Text With Media","story":"Docs","parameters":{"__id":"molecules-text-with-media--docs","docsOnly":true,"fileName":"./components/02-molecules/text-with-media/text-with-media.stories.js"}},"molecules-text-with-media--text-with-media":{"id":"molecules-text-with-media--text-with-media","name":"Text With Media","title":"Molecules/Text With Media","importPath":"./components/02-molecules/text-with-media/text-with-media.stories.js","tags":["story"],"kind":"Molecules/Text With Media","story":"Text With Media","parameters":{"__id":"molecules-text-with-media--text-with-media","docsOnly":false,"fileName":"./components/02-molecules/text-with-media/text-with-media.stories.js"}},"organisms-grids--docs":{"id":"organisms-grids--docs","title":"Organisms/Grids","name":"Docs","importPath":"./components/03-organisms/grid/grids.stories.js","tags":["docs","autodocs"],"storiesImports":[],"kind":"Organisms/Grids","story":"Docs","parameters":{"__id":"organisms-grids--docs","docsOnly":true,"fileName":"./components/03-organisms/grid/grids.stories.js"}},"organisms-grids--default-grid":{"id":"organisms-grids--default-grid","name":"Default Grid","title":"Organisms/Grids","importPath":"./components/03-organisms/grid/grids.stories.js","tags":["story"],"kind":"Organisms/Grids","story":"Default Grid","parameters":{"__id":"organisms-grids--default-grid","docsOnly":false,"fileName":"./components/03-organisms/grid/grids.stories.js"}},"organisms-site--docs":{"id":"organisms-site--docs","title":"Organisms/Site","name":"Docs","importPath":"./components/03-organisms/site/site.stories.js","tags":["docs","autodocs"],"storiesImports":[],"kind":"Organisms/Site","story":"Docs","parameters":{"__id":"organisms-site--docs","docsOnly":true,"fileName":"./components/03-organisms/site/site.stories.js"}},"organisms-site--footer":{"id":"organisms-site--footer","name":"Footer","title":"Organisms/Site","importPath":"./components/03-organisms/site/site.stories.js","tags":["story"],"kind":"Organisms/Site","story":"Footer","parameters":{"__id":"organisms-site--footer","docsOnly":false,"fileName":"./components/03-organisms/site/site.stories.js"}},"organisms-site--header":{"id":"organisms-site--header","name":"Header","title":"Organisms/Site","importPath":"./components/03-organisms/site/site.stories.js","tags":["story"],"kind":"Organisms/Site","story":"Header","parameters":{"__id":"organisms-site--header","docsOnly":false,"fileName":"./components/03-organisms/site/site.stories.js"}},"templates-layouts--docs":{"id":"templates-layouts--docs","title":"Templates/Layouts","name":"Docs","importPath":"./components/04-templates/layouts.stories.js","tags":["docs","autodocs"],"storiesImports":[],"kind":"Templates/Layouts","story":"Docs","parameters":{"__id":"templates-layouts--docs","docsOnly":true,"fileName":"./components/04-templates/layouts.stories.js"}},"templates-layouts--full-width":{"id":"templates-layouts--full-width","name":"Full Width","title":"Templates/Layouts","importPath":"./components/04-templates/layouts.stories.js","tags":["story"],"kind":"Templates/Layouts","story":"Full Width","parameters":{"__id":"templates-layouts--full-width","docsOnly":false,"fileName":"./components/04-templates/layouts.stories.js"}},"templates-layouts--with-sidebar":{"id":"templates-layouts--with-sidebar","name":"With Sidebar","title":"Templates/Layouts","importPath":"./components/04-templates/layouts.stories.js","tags":["story"],"kind":"Templates/Layouts","story":"With Sidebar","parameters":{"__id":"templates-layouts--with-sidebar","docsOnly":false,"fileName":"./components/04-templates/layouts.stories.js"}},"templates-place-holder--docs":{"id":"templates-place-holder--docs","title":"Templates/Place Holder","name":"Docs","importPath":"./components/04-templates/placeholder/place-holder.stories.js","tags":["docs","autodocs"],"storiesImports":[],"kind":"Templates/Place Holder","story":"Docs","parameters":{"__id":"templates-place-holder--docs","docsOnly":true,"fileName":"./components/04-templates/placeholder/place-holder.stories.js"}},"templates-place-holder--place-holder":{"id":"templates-place-holder--place-holder","name":"Place Holder","title":"Templates/Place Holder","importPath":"./components/04-templates/placeholder/place-holder.stories.js","tags":["story"],"kind":"Templates/Place Holder","story":"Place Holder","parameters":{"__id":"templates-place-holder--place-holder","docsOnly":false,"fileName":"./components/04-templates/placeholder/place-holder.stories.js"}},"pages-content-types--docs":{"id":"pages-content-types--docs","title":"Pages/Content Types","name":"Docs","importPath":"./components/05-pages/content-types/content-types.stories.js","tags":["docs","autodocs"],"storiesImports":[],"kind":"Pages/Content Types","story":"Docs","parameters":{"__id":"pages-content-types--docs","docsOnly":true,"fileName":"./components/05-pages/content-types/content-types.stories.js"}},"pages-content-types--article":{"id":"pages-content-types--article","name":"Article","title":"Pages/Content Types","importPath":"./components/05-pages/content-types/content-types.stories.js","tags":["story"],"kind":"Pages/Content Types","story":"Article","parameters":{"__id":"pages-content-types--article","docsOnly":false,"fileName":"./components/05-pages/content-types/content-types.stories.js"}},"pages-landing-pages--docs":{"id":"pages-landing-pages--docs","title":"Pages/Landing Pages","name":"Docs","importPath":"./components/05-pages/landing-pages/landing-pages.stories.js","tags":["docs","autodocs"],"storiesImports":[],"kind":"Pages/Landing Pages","story":"Docs","parameters":{"__id":"pages-landing-pages--docs","docsOnly":true,"fileName":"./components/05-pages/landing-pages/landing-pages.stories.js"}},"pages-landing-pages--home-page":{"id":"pages-landing-pages--home-page","name":"Home Page","title":"Pages/Landing Pages","importPath":"./components/05-pages/landing-pages/landing-pages.stories.js","tags":["story"],"kind":"Pages/Landing Pages","story":"Home Page","parameters":{"__id":"pages-landing-pages--home-page","docsOnly":false,"fileName":"./components/05-pages/landing-pages/landing-pages.stories.js"}}}}
